{"id":"cursed-hiragana","name":"Basics: Hiragana","words":[{"id":"03042","romaji":["a"],"reading":{"on":[],"kun":["\u3042"]},"meaning":["a"]},{"id":"03044","romaji":["i"],"reading":{"on":[],"kun":["\u3044"]},"meaning":["i"]},{"id":"03046","romaji":["u"],"reading":{"on":[],"kun":["\u3046"]},"meaning":["u"]},{"id":"03048","romaji":["e"],"reading":{"on":[],"kun":["\u3048"]},"meaning":["e"]},{"id":"0304a","romaji":["o"],"reading":{"on":[],"kun":["\u304a"]},"meaning":["o"]},{"id":"0304b","romaji":["ka"],"reading":{"on":[],"kun":["\u304b"]},"meaning":["ka"]},{"id":"0304d","romaji":["ki"],"reading":{"on":[],"kun":["\u304d"]},"meaning":["ki"]},{"id":"0304f","romaji":["ku"],"reading":{"on":[],"kun":["\u304f"]},"meaning":["ku"]},{"id":"03051","romaji":["ke"],"reading":{"on":[],"kun":["\u3051"]},"meaning":["ke"]},{"id":"03053","romaji":["ko"],"reading":{"on":[],"kun":["\u3053"]},"meaning":["ko"]},{"id":"03055","romaji":["sa"],"reading":{"on":[],"kun":["\u3055"]},"meaning":["sa"]},{"id":"03057","romaji":["shi"],"reading":{"on":[],"kun":["\u3057"]},"meaning":["shi"]},{"id":"03059","romaji":["su"],"reading":{"on":[],"kun":["\u3059"]},"meaning":["su"]},{"id":"0305b","romaji":["se"],"reading":{"on":[],"kun":["\u305b"]},"meaning":["se"]},{"id":"0305d","romaji":["so"],"reading":{"on":[],"kun":["\u305d"]},"meaning":["so"]},{"id":"0305f","romaji":["ta"],"reading":{"on":[],"kun":["\u305f"]},"meaning":["ta"]},{"id":"03061","romaji":["chi"],"reading":{"on":[],"kun":["\u3061"]},"meaning":["chi"]},{"id":"03064","romaji":["tsu"],"reading":{"on":[],"kun":["\u3064"]},"meaning":["tsu"]},{"id":"03066","romaji":["te"],"reading":{"on":[],"kun":["\u3066"]},"meaning":["te"]},{"id":"03068","romaji":["to"],"reading":{"on":[],"kun":["\u3068"]},"meaning":["to"]},{"id":"0306a","romaji":["na"],"reading":{"on":[],"kun":["\u306a"]},"meaning":["na"]},{"id":"0306b","romaji":["ni"],"reading":{"on":[],"kun":["\u306b"]},"meaning":["ni"]},{"id":"0306c","romaji":["nu"],"reading":{"on":[],"kun":["\u306c"]},"meaning":["nu"]},{"id":"0306d","romaji":["ne"],"reading":{"on":[],"kun":["\u306d"]},"meaning":["ne"]},{"id":"0306e","romaji":["no"],"reading":{"on":[],"kun":["\u306e"]},"meaning":["no"]},{"id":"0306f","romaji":["ha"],"reading":{"on":[],"kun":["\u306f"]},"meaning":["ha"]},{"id":"03072","romaji":["hi"],"reading":{"on":[],"kun":["\u3072"]},"meaning":["hi"]},{"id":"03075","romaji":["fu"],"reading":{"on":[],"kun":["\u3075"]},"meaning":["fu"]},{"id":"03078","romaji":["he"],"reading":{"on":[],"kun":["\u3078"]},"meaning":["he"]},{"id":"0307b","romaji":["ho"],"reading":{"on":[],"kun":["\u307b"]},"meaning":["ho"]},{"id":"0307e","romaji":["ma"],"reading":{"on":[],"kun":["\u307e"]},"meaning":["ma"]},{"id":"0307f","romaji":["mi"],"reading":{"on":[],"kun":["\u307f"]},"meaning":["mi"]},{"id":"03080","romaji":["mu"],"reading":{"on":[],"kun":["\u3080"]},"meaning":["mu"]},{"id":"03081","romaji":["me"],"reading":{"on":[],"kun":["\u3081"]},"meaning":["me"]},{"id":"03082","romaji":["mo"],"reading":{"on":[],"kun":["\u3082"]},"meaning":["mo"]},{"id":"03084","romaji":["ya"],"reading":{"on":[],"kun":["\u3084"]},"meaning":["ya"]},{"id":"03086","romaji":["yu"],"reading":{"on":[],"kun":["\u3086"]},"meaning":["yu"]},{"id":"03088","romaji":["yo"],"reading":{"on":[],"kun":["\u3088"]},"meaning":["yo"]},{"id":"03089","romaji":["ra"],"reading":{"on":[],"kun":["\u3089"]},"meaning":["ra"]},{"id":"0308a","romaji":["ri"],"reading":{"on":[],"kun":["\u308a"]},"meaning":["ri"]},{"id":"0308b","romaji":["ru"],"reading":{"on":[],"kun":["\u308b"]},"meaning":["ru"]},{"id":"0308c","romaji":["re"],"reading":{"on":[],"kun":["\u308c"]},"meaning":["re"]},{"id":"0308d","romaji":["ro"],"reading":{"on":[],"kun":["\u308d"]},"meaning":["ro"]},{"id":"0308f","romaji":["wa"],"reading":{"on":[],"kun":["\u308f"]},"meaning":["wa"]},{"id":"03092","romaji":["wo"],"reading":{"on":[],"kun":["\u3092"]},"meaning":["(w)o"]},{"id":"03093","romaji":["n"],"reading":{"on":[],"kun":["\u3093"]},"meaning":["n"]}]}